{
  "parent": "minecraft:story/upgrade_tools",
  "criteria": {
    "got_tin_ingot": {
      "conditions": {
        "items": [
          {
            "items": "bronze:tin_ingot"
          }
        ]
      },
      "trigger": "minecraft:inventory_changed"
    }
  },
  "display": {
    "description": {
      "translate": "advancement.bronze.got_tin_ingot.description"
    },
    "icon": {
      "count": 1,
      "id": "bronze:tin_ingot"
    },
    "title": {
      "translate": "advancement.bronze.got_tin_ingot.title"
    }
  },
  "requirements": [
    [
      "got_tin_ingot"
    ]
  ],
  "rewards": {
    "recipes": [
      "bronze:tin_block"
    ]
  },
  "sends_telemetry_event": true
}